gh_hooks_utils/__init__.py
gh_hooks_utils/errors.py
gh_hooks_utils/logger.py
gh_hooks_utils/py.typed
gh_hooks_utils/validators.py
gh_hooks_utils/version.py
gh_hooks_utils/auth/__init__.py
gh_hooks_utils/auth/app_auth.py
gh_hooks_utils/auth/token.py
gh_hooks_utils/events/__init__.py
gh_hooks_utils/events/events_enum.py
gh_hooks_utils/headers/__init__.py
gh_hooks_utils/headers/events.py
gh_hooks_utils/headers/headers.py
gh_hooks_utils/payloads/__init__.py
gh_hooks_utils/payloads/account.py
gh_hooks_utils/payloads/author_association_enum.py
gh_hooks_utils/payloads/enterprise.py
gh_hooks_utils/payloads/installation.py
gh_hooks_utils/payloads/label.py
gh_hooks_utils/payloads/license.py
gh_hooks_utils/payloads/organization.py
gh_hooks_utils/payloads/permission.py
gh_hooks_utils/payloads/repository.py
gh_hooks_utils/payloads/repository_selection_enum.py
gh_hooks_utils/payloads/user.py
gh_hooks_utils/payloads/discussion_comment/__init__.py
gh_hooks_utils/payloads/discussion_comment/comment.py
gh_hooks_utils/payloads/discussion_comment/discussion_comment_action_enum.py
gh_hooks_utils/payloads/discussion_comment/discussion_comment_event.py
gh_hooks_utils/payloads/discussions/__init__.py
gh_hooks_utils/payloads/discussions/answer.py
gh_hooks_utils/payloads/discussions/category.py
gh_hooks_utils/payloads/discussions/discussion.py
gh_hooks_utils/payloads/discussions/discussion_action_enum.py
gh_hooks_utils/payloads/discussions/discussion_event.py
gh_hooks_utils/payloads/discussions/discussion_state_enum.py
gh_hooks_utils/payloads/discussions/discussion_state_reason_enum.py
gh_hooks_utils/payloads/discussions/reaction.py
gh_hooks_utils/payloads/install/__init__.py
gh_hooks_utils/payloads/install/installation_action_enum.py
gh_hooks_utils/payloads/install/installation_event.py
gh_hooks_utils/payloads/installation_repositories/__init__.py
gh_hooks_utils/payloads/installation_repositories/installation_repositories_action_enum.py
gh_hooks_utils-0.3.6.dist-info/METADATA
gh_hooks_utils-0.3.6.dist-info/WHEEL
gh_hooks_utils-0.3.6.dist-info/licenses/LICENSE
gh_hooks_utils-0.3.6.dist-info/RECORD
